<contents>
<item>
    <file>graphics_driver.c</file>
    This file holds the X11-dependent low-level
			driver-funtions of graphics.library.

</item>

<item>
    <file>graphics_internal.h</file>
    Here is the definition of the driver-internal data
			structure which is stored in RastPort-longreserved[0].

</item>

<item>
    <file>intuition_driver.c</file>
    This file holds the X11-dependent low-level
			driver-functions of intuition.library.

</item>

<item>
    <file>mmakefile.src</file>
    This is the mmakefile source for config/x11.
</item>
</contents>
